palmoni_core/__init__.py
palmoni_core/cli/__init__.py
palmoni_core/cli/commands.py
palmoni_core/core/__init__.py
palmoni_core/core/config.py
palmoni_core/core/database.py
palmoni_core/core/expander.py
palmoni_core/data/snippets.db
palmoni_core/tests/__init__.py
palmoni_core/tests/test_cli.py
palmoni_core/tests/test_config.py
palmoni_core/tests/test_database.py
palmoni_core/tests/test_expander.py
palmoni-0.1.3.dist-info/METADATA
palmoni-0.1.3.dist-info/WHEEL
palmoni-0.1.3.dist-info/entry_points.txt
palmoni-0.1.3.dist-info/licenses/LICENSE
palmoni-0.1.3.dist-info/RECORD
