Metadata-Version: 2.4
Name: palmoni
Version: 0.1.3
Author-email: daniel-wallace-personal <wallace.danielk@gmail.com>
License: MIT
License-File: LICENSE
Requires-Python: >=3.11
Requires-Dist: duckdb<2.0.0,>=1.3.2
Requires-Dist: pynput<2.0.0,>=1.8.1
Requires-Dist: pyyaml<7.0.0,>=6.0.2
Requires-Dist: typer<0.17.0,>=0.16.1
Requires-Dist: watchdog<7.0.0,>=6.0.0
Provides-Extra: dev
Requires-Dist: pytest-mock<4.0.0,>=3.14.1; extra == 'dev'
Requires-Dist: pytest<9.0.0,>=8.4.1; extra == 'dev'
